{
  "tokens": [
    {
      "id": 1,
      "name": "VC #1",
      "symbol": "VCNFT",
      "description": "DrinkUP",
      "image": "https://drinkup-water.s3.us-west-2.amazonaws.com/nft/cola-test1.png",
      "external_url": "https://www.drinkup.link",
      "properties": {
        "files": [
          {
            "uri": "https://drinkup-water.s3.us-west-2.amazonaws.com/nft/cola-test1.png",
            "type": "image/png"
          }
        ],
        "category": "image"
      },
      "attributes": []
    },
    {
      "id": 2,
      "name": "VC #2",
      "symbol": "VCNFT",
      "description": "DrinkUP",
      "image": "https://drinkup-water.s3.us-west-2.amazonaws.com/nft/cola-test1.png",
      "external_url": "https://www.drinkup.link",
      "properties": {
        "files": [
          {
            "uri": "https://drinkup-water.s3.us-west-2.amazonaws.com/nft/cola-test1.png",
            "type": "image/png"
          }
        ],
        "category": "image"
      },
      "attributes": []
    },
    {
      "id": 3,
      "name": "VC #3",
      "symbol": "VCNFT",
      "description": "DrinkUP",
      "image": "https://drinkup-water.s3.us-west-2.amazonaws.com/nft/cola-test1.png",
      "external_url": "https://www.drinkup.link",
      "properties": {
        "files": [
          {
            "uri": "https://drinkup-water.s3.us-west-2.amazonaws.com/nft/cola-test1.png",
            "type": "image/png"
          }
        ],
        "category": "image"
      },
      "attributes": []
    }
  ]
}